timechecker/__init__.py
timechecker/cli.py
timechecker/core.py
timechecker_cli_teddy-1.0.0.dist-info/licenses/LICENSE
timechecker_cli_teddy-1.0.0.dist-info/METADATA
timechecker_cli_teddy-1.0.0.dist-info/WHEEL
timechecker_cli_teddy-1.0.0.dist-info/entry_points.txt
timechecker_cli_teddy-1.0.0.dist-info/top_level.txt
timechecker_cli_teddy-1.0.0.dist-info/RECORD
