Metadata-Version: 2.4
Name: timechecker-cli-teddy
Version: 1.0.0
Summary: CLI tool for checking current time in different timezones
Home-page: https://github.com/timechecker/timechecker
Author: Timechecker Team
Author-email: Timechecker Team <team@timechecker.dev>
License: MIT
Project-URL: Homepage, https://github.com/timechecker/timechecker
Project-URL: Bug Reports, https://github.com/timechecker/timechecker/issues
Project-URL: Source, https://github.com/timechecker/timechecker
Classifier: Development Status :: 5 - Production/Stable
Classifier: Intended Audience :: Developers
Classifier: License :: OSI Approved :: MIT License
Classifier: Operating System :: OS Independent
Classifier: Programming Language :: Python :: 3
Classifier: Programming Language :: Python :: 3.7
Classifier: Programming Language :: Python :: 3.8
Classifier: Programming Language :: Python :: 3.9
Classifier: Programming Language :: Python :: 3.10
Classifier: Programming Language :: Python :: 3.11
Classifier: Programming Language :: Python :: 3.12
Requires-Python: >=3.7
License-File: LICENSE
Requires-Dist: pytz>=2023.3
Dynamic: author
Dynamic: home-page
Dynamic: license-file
Dynamic: requires-python
